MANIFEST.in
README.rst
setup.py
src/simple_aes.py
src/simple_aes.egg-info/PKG-INFO
src/simple_aes.egg-info/SOURCES.txt
src/simple_aes.egg-info/dependency_links.txt
src/simple_aes.egg-info/requires.txt
src/simple_aes.egg-info/top_level.txt