Metadata-Version: 1.1
Name: simple-aes
Version: 0.4.7
Summary: Very simple pycrypto AES helper.
Home-page: http://github.com/mosquito/simpleaes
Author: Dmitry Orlov <me@mosquito.su>
Author-email: me@mosquito.su
License: MIT
Platform: all
Classifier: Environment :: Console
Classifier: Programming Language :: Python
